llava/__init__.py
llava/constants.py
llava/conversation.py
llava/mm_utils.py
llava/utils.py
llava/eval/eval_gpt_review.py
llava/eval/eval_gpt_review_bench.py
llava/eval/eval_gpt_review_visual.py
llava/eval/eval_pope.py
llava/eval/eval_science_qa.py
llava/eval/eval_science_qa_gpt4.py
llava/eval/eval_science_qa_gpt4_requery.py
llava/eval/eval_textvqa.py
llava/eval/generate_webpage_data_from_table.py
llava/eval/m4c_evaluator.py
llava/eval/model_qa.py
llava/eval/model_vqa.py
llava/eval/model_vqa_loader.py
llava/eval/model_vqa_mmbench.py
llava/eval/model_vqa_science.py
llava/eval/qa_baseline_gpt35.py
llava/eval/run_llava.py
llava/eval/summarize_gpt_review.py
llava/model/__init__.py
llava/model/apply_delta.py
llava/model/builder.py
llava/model/consolidate.py
llava/model/llava_arch.py
llava/model/make_delta.py
llava/model/utils.py
llava/model/language_model/llava_llama.py
llava/model/language_model/llava_mistral.py
llava/model/language_model/llava_mpt.py
llava/model/multimodal_encoder/builder.py
llava/model/multimodal_encoder/clip_encoder.py
llava/model/multimodal_projector/builder.py
llava/serve/__init__.py
llava/serve/cli.py
llava/serve/controller.py
llava/serve/gradio_web_server.py
llava/serve/model_worker.py
llava/serve/new_gws.py
llava/serve/register_worker.py
llava/serve/sglang_worker.py
llava/serve/test_message.py
llava/train/llama_flash_attn_monkey_patch.py
llava/train/llama_xformers_attn_monkey_patch.py
llava/train/llava2parquet_to_Luke.py
llava/train/llava_trainer.py
llava/train/train.py
llava/train/train_from_s3_to_Luke.py
llava/train/train_mem.py
llava/train/train_s3.py
llava/train/train_together.py
llava/train/train_xformers.py
uground_demo_test-4.4.dist-info/LICENSE
uground_demo_test-4.4.dist-info/METADATA
uground_demo_test-4.4.dist-info/WHEEL
uground_demo_test-4.4.dist-info/top_level.txt
uground_demo_test-4.4.dist-info/RECORD
